CHANGES.rst
COPYING.txt
pyramid_cloudflare_access/__init__.py
pyramid_cloudflare_access/tests/__init__.py
pyramid_cloudflare_access/tests/conftest.py
pyramid_cloudflare_access/tests/test_access.py
pyramid_cloudflare_access-1.2.dist-info/COPYING.txt
pyramid_cloudflare_access-1.2.dist-info/METADATA
pyramid_cloudflare_access-1.2.dist-info/WHEEL
pyramid_cloudflare_access-1.2.dist-info/RECORD
